mailcatcher.py
mailcatcher-0.1.6.dist-info/DESCRIPTION.rst
mailcatcher-0.1.6.dist-info/METADATA
mailcatcher-0.1.6.dist-info/RECORD
mailcatcher-0.1.6.dist-info/WHEEL
mailcatcher-0.1.6.dist-info/metadata.json
mailcatcher-0.1.6.dist-info/top_level.txt
