Metadata-Version: 2.0
Name: mailcatcher
Version: 0.1.6
Summary: Simple mailcatcher client for Python.
Home-page: https://github.com/kamiazya/py-mailcatcher
Author: kamiazya
Author-email: yuki@kamiazya.tech
License: MIT
Keywords: mailcatcher development rx
Platform: UNKNOWN
Classifier: Programming Language :: Python :: 3.6
Requires-Dist: requests (>=2.18.4)
Requires-Dist: rx (>=1.6.1)
Requires-Dist: websocket-client (>=0.47.0)
